potentiostat/__init__.py
potentiostat/potentiostat.py
iorodeo_potentiostat-0.0.9.dist-info/LICENSE.txt
iorodeo_potentiostat-0.0.9.dist-info/METADATA
iorodeo_potentiostat-0.0.9.dist-info/WHEEL
iorodeo_potentiostat-0.0.9.dist-info/top_level.txt
iorodeo_potentiostat-0.0.9.dist-info/RECORD
